Incantation-0.4.1.dist-info/DESCRIPTION.rst
Incantation-0.4.1.dist-info/METADATA
Incantation-0.4.1.dist-info/RECORD
Incantation-0.4.1.dist-info/WHEEL
Incantation-0.4.1.dist-info/metadata.json
Incantation-0.4.1.dist-info/top_level.txt
incantation/__init__.py
incantation/abst.py
incantation/base.py
incantation/err.py
incantation/utils.py
incantation/CSS/Color.py
incantation/CSS/Grid.py
incantation/CSS/Helpers.py
incantation/CSS/Media.py
incantation/CSS/Pulse.py
incantation/CSS/Shadow.py
incantation/CSS/Table.py
incantation/CSS/Typography.py
incantation/CSS/__init__.py
incantation/Component/Badges.py
incantation/Component/Breadcrumb.py
incantation/Component/Buttons.py
incantation/Component/Cards.py
incantation/Component/Collections.py
incantation/Component/Forms.py
incantation/Component/Icons.py
incantation/Component/__init__.py
incantation/Frequently/__init__.py
incantation/Javascript/Carousel.py
incantation/Javascript/SideNav.py
incantation/Javascript/__init__.py
incantation/Templates/Card.py
incantation/Templates/HTML.py
incantation/Templates/Page.py
incantation/Templates/Text.py
incantation/Templates/__init__.py
