Metadata-Version: 2.0
Name: Incantation
Version: 0.4.1
Summary: Python Object Design about Website. Make Developing websites like saying incantations.
Home-page: https://github.com/thautwarm/Incantation
Author: thautwarm
Author-email: twshere@outlook.com
License: MIT
Keywords: website,web-design
Platform: any
Classifier: Programming Language :: Python :: 3.6
Classifier: Programming Language :: Python :: Implementation :: CPython
